[
    {
        "dispo": 220,
        "max": 270,
        "timestamp": "2023-09-18 09:28:39"
    },
    {
        "dispo": 220,
        "max": 270,
        "timestamp": "2023-09-18 09:28:42"
    },
    {
        "dispo": 220,
        "max": 270,
        "timestamp": "2023-09-18 09:28:44"
    },
    {
        "dispo": 220,
        "max": 270,
        "timestamp": "2023-09-18 09:28:47"
    },
    {
        "dispo": 220,
        "max": 270,
        "timestamp": "2023-09-18 09:28:50"
    },
    {
        "dispo": 220,
        "max": 270,
        "timestamp": "2023-09-18 09:28:54"
    },
    {
        "dispo": 220,
        "max": 270,
        "timestamp": "2023-09-18 09:29:04"
    },
    {
        "dispo": 222,
        "max": 270,
        "timestamp": "2023-09-18 09:41:35"
    },
    {
        "dispo": 222,
        "max": 270,
        "timestamp": "2023-09-18 09:41:35"
    },
    {
        "dispo": 221,
        "max": 270,
        "timestamp": "2023-09-18 09:51:37"
    },
    {
        "dispo": 221,
        "max": 270,
        "timestamp": "2023-09-18 09:51:57"
    },
    {
        "dispo": 221,
        "max": 270,
        "timestamp": "2023-09-18 09:52:03"
    },
    {
        "dispo": 221,
        "max": 270,
        "timestamp": "2023-09-18 09:52:36"
    },
    {
        "dispo": 221,
        "max": 270,
        "timestamp": "2023-09-18 09:52:36"
    },
    {
        "dispo": 225,
        "max": 270,
        "timestamp": "2023-09-18 10:02:38"
    }
]