[
    {
        "dispo": 1045,
        "max": 1182,
        "timestamp": "2023-09-18 18:04:46"
    },
    {
        "dispo": 1046,
        "max": 1182,
        "timestamp": "2023-09-18 18:07:06"
    },
    {
        "dispo": 1046,
        "max": 1182,
        "timestamp": "2023-09-18 18:07:40"
    },
    {
        "dispo": 1046,
        "max": 1182,
        "timestamp": "2023-09-18 18:07:49"
    },
    {
        "dispo": 1047,
        "max": 1182,
        "timestamp": "2023-09-18 18:09:57"
    },
    {
        "dispo": 1058,
        "max": 1182,
        "timestamp": "2023-09-18 18:54:06"
    },
    {
        "dispo": 1060,
        "max": 1182,
        "timestamp": "2023-09-18 19:25:53"
    },
    {
        "dispo": 1061,
        "max": 1182,
        "timestamp": "2023-09-18 19:43:23"
    },
    {
        "dispo": 1060,
        "max": 1182,
        "timestamp": "2023-09-18 20:15:36"
    },
    {
        "dispo": 1060,
        "max": 1182,
        "timestamp": "2023-09-18 21:14:16"
    },
    {
        "dispo": 1060,
        "max": 1182,
        "timestamp": "2023-09-18 21:20:27"
    },
    {
        "dispo": 1060,
        "max": 1182,
        "timestamp": "2023-09-18 21:21:24"
    },
    {
        "dispo": 1060,
        "max": 1182,
        "timestamp": "2023-09-18 21:38:42"
    }
]